ArquiteturaDeComputadores/Arquitetura1/GuiasResolvidos/Guia11_Felipe_Gabriel_de_Carvalho_1543536/Guia_1101.v
`timescale 1ns/1ps
`define found 1
`define notfound 0

// Módulo Mealy que detecta a sequência "1101"
module mealy_1101 (y, x, clk, reset);
  output reg y;
  input x, clk, reset;

  parameter
    start = 2'b00,
    id1 = 2'b01,
    id11 = 2'b11,
    id110 = 2'b10;

  reg [1:0] current_state, next_state;

  // Lógica do próximo estado e saída (Mealy)
  always @(x or current_state) begin
    y = `notfound;
    case (current_state)
      start: next_state = x ? id1 : start;
      id1: next_state = x ? id11 : start;
      id11: next_state = x ? id11 : id110;
      id110: begin
        next_state = x ? id1 : start;
        y = x ? `found : `notfound;
      end
      default: next_state = start;
    endcase
  end

  // Atualização de estado
  always @(posedge clk or negedge reset) begin
    if (!reset)
      current_state <= start;
    else
      current_state <= next_state;
  end
endmodule

// Testbench incluído no mesmo arquivo
module tb_mealy_1101;
  reg x, clk, reset;
  wire y;

  // Instanciando o módulo
  mealy_1101 dut (.y(y), .x(x), .clk(clk), .reset(reset));

  // Gerador de clock
  always #5 clk = ~clk;

  initial begin
    // Dump para GTKWave (opcional)
    $dumpfile("wave.vcd");
    $dumpvars(0, tb_mealy_1101);

    // Inicialização
    clk = 0;
    reset = 0;
    x = 0;

    // Reset
    #10 reset = 1;

    // Sequência de teste: 1101
    #10 x = 1;
    #10 x = 1;
    #10 x = 0;
    #10 x = 1; // Aqui y deve ser 1

    // Sequência extra para observar comportamento
    #10 x = 1;
    #10 x = 0;
    #10 x = 1;
    #10 x = 1;

    #20 $finish;
  end
endmodule

ArquiteturaDeComputadores/Arquitetura1/GuiasResolvidos/Guia11_Felipe_Gabriel_de_Carvalho_1543536/wave.vcd
$date
	Fri May 09 17:20:17 2025
$end
$version
	Icarus Verilog
$end
$timescale
	1ps
$end
$scope module tb_mealy_1101 $end
$var wire 1 ! y $end
$var reg 1 " clk $end
$var reg 1 # reset $end
$var reg 1 $ x $end
$scope module dut $end
$var wire 1 " clk $end
$var wire 1 # reset $end
$var wire 1 $ x $end
$var parameter 2 % id1 $end
$var parameter 2 & id11 $end
$var parameter 2 ' id110 $end
$var parameter 2 ( start $end
$var reg 2 ) current_state [1:0] $end
$var reg 2 * next_state [1:0] $end
$var reg 1 ! y $end
$upscope $end
$upscope $end
$enddefinitions $end
$comment Show the parameter values. $end
$dumpall
b0 (
b10 '
b11 &
b1 %
$end
#0
$dumpvars
b0 *
b0 )
0$
0#
0"
0!
$end
#5000
1"
#10000
0"
1#
#15000
1"
#20000
b1 *
0"
1$
#25000
b11 *
b1 )
1"
#30000
0"
#35000
b11 )
1"
#40000
b10 *
0"
0$
#45000
b0 *
b10 )
1"
#50000
1!
b1 *
0"
1$
#55000
b11 *
0!
b1 )
1"
#60000
0"
#65000
b11 )
1"
#70000
b10 *
0"
0$
#75000
b0 *
b10 )
1"
#80000
1!
b1 *
0"
1$
#85000
b11 *
0!
b1 )
1"
#90000
0"
#95000
b11 )
1"
